odoo9_addon_pos_price_to_weight-9.0.1.0.0-py2.7-nspkg.pth
odoo9_addon_pos_price_to_weight-9.0.1.0.0.dist-info/DESCRIPTION.rst
odoo9_addon_pos_price_to_weight-9.0.1.0.0.dist-info/METADATA
odoo9_addon_pos_price_to_weight-9.0.1.0.0.dist-info/RECORD
odoo9_addon_pos_price_to_weight-9.0.1.0.0.dist-info/WHEEL
odoo9_addon_pos_price_to_weight-9.0.1.0.0.dist-info/metadata.json
odoo9_addon_pos_price_to_weight-9.0.1.0.0.dist-info/namespace_packages.txt
odoo9_addon_pos_price_to_weight-9.0.1.0.0.dist-info/top_level.txt
odoo_addons/pos_price_to_weight/README.rst
odoo_addons/pos_price_to_weight/__init__.py
odoo_addons/pos_price_to_weight/__openerp__.py
odoo_addons/pos_price_to_weight/data/barcode_rule.xml
odoo_addons/pos_price_to_weight/demo/product_product.xml
odoo_addons/pos_price_to_weight/i18n/fr.po
odoo_addons/pos_price_to_weight/models/__init__.py
odoo_addons/pos_price_to_weight/models/barcode_rule.py
odoo_addons/pos_price_to_weight/static/description/barcode_rule.png
odoo_addons/pos_price_to_weight/static/description/icon.png
odoo_addons/pos_price_to_weight/static/description/pos_test_1.png
odoo_addons/pos_price_to_weight/static/description/pos_test_2.png
odoo_addons/pos_price_to_weight/static/src/js/models.js
odoo_addons/pos_price_to_weight/static/src/js/screens.js
odoo_addons/pos_price_to_weight/static/src/xml/templates.xml
